quick_vantage/__init__.py
quick_vantage/__main__.py
quick_vantage-0.0.2.dist-info/METADATA
quick_vantage-0.0.2.dist-info/WHEEL
quick_vantage-0.0.2.dist-info/entry_points.txt
quick_vantage-0.0.2.dist-info/licenses/LICENSE
quick_vantage-0.0.2.dist-info/RECORD
