Metadata-Version: 2.4
Name: quick-vantage
Version: 0.0.2
Summary: Linux port of Lenovo Vantage
Project-URL: Homepage, https://github.com/symbian-bro/quick-vantage-python-flavour
Project-URL: Bug Tracker, https://github.com/symbian-bro/quick-vantage-python-flavour/issues
Author-email: SIDDHARTH K P <siddharth.alakkode@proton.me>
License-File: LICENSE
Classifier: License :: OSI Approved :: MIT License
Classifier: Operating System :: OS Independent
Classifier: Programming Language :: Python :: 3
Requires-Python: >=3.7
